autodoc2/__init__.py
autodoc2/analysis.py
autodoc2/astroid_utils.py
autodoc2/cli.py
autodoc2/config.py
autodoc2/db.py
autodoc2/py.typed
autodoc2/resolve_all.py
autodoc2/utils.py
autodoc2/render/__init__.py
autodoc2/render/base.py
autodoc2/render/fern_.py
autodoc2/render/myst_.py
py2fern-0.1.5.dist-info/entry_points.txt
py2fern-0.1.5.dist-info/licenses/LICENSE
py2fern-0.1.5.dist-info/WHEEL
py2fern-0.1.5.dist-info/METADATA
py2fern-0.1.5.dist-info/RECORD
