Metadata-Version: 2.4
Name: py2fern
Version: 0.1.5
Summary: Generate Fern documentation from Python packages using static analysis.
Keywords: python,documentation,fern,api,static-analysis
Author-email: Ryan Stephen <ryanstep@buildwithfern.com>
Requires-Python: >=3.8
Classifier: License :: OSI Approved :: MIT License
Classifier: Programming Language :: Python :: 3
License-File: LICENSE
Requires-Dist: astroid>=2.7,<4
Requires-Dist: tomli; python_version<'3.11'
Requires-Dist: typing-extensions
Requires-Dist: typer[all]
Requires-Dist: PyYAML
Requires-Dist: pytest ; extra == "testing"
Requires-Dist: pytest-regressions ; extra == "testing"
Requires-Dist: pytest-cov ; extra == "testing"
Requires-Dist: PyYAML ; extra == "testing"
Requires-Dist: types-PyYAML ; extra == "testing"
Project-URL: Home, https://github.com/fern-api/py2fern
Provides-Extra: testing
